resumy/config.example.yaml
resumy/resumy.py
resumy/schemas/jsonresume.yaml
resumy/schemas/resumy.yaml
resumy/themes/prairie/icons.css
resumy/themes/prairie/theme.css
resumy/themes/prairie/theme.html
resumy/themes/prairie/fonts/Roboto-Bold.woff2
resumy/themes/prairie/fonts/Roboto-Regular.woff2
resumy/themes/prairie/fonts/prairie.woff2
resumy-0.1.2.dist-info/LICENSE
resumy-0.1.2.dist-info/METADATA
resumy-0.1.2.dist-info/WHEEL
resumy-0.1.2.dist-info/entry_points.txt
resumy-0.1.2.dist-info/top_level.txt
resumy-0.1.2.dist-info/RECORD
