Metadata-Version: 2.1
Name: resumy
Version: 0.1.2
Summary: Resume builder
Author-email: Alex Laurent <alex@i42.sh>
License: MIT License
Project-URL: homepage, https://github.com/alexlren/resumy
Keywords: resume,cv
Classifier: Programming Language :: Python :: 3.8
Requires-Python: >=3.8
License-File: LICENSE
Requires-Dist: PyYAML ==6.0
Requires-Dist: Jinja2 >=3.1.2
Requires-Dist: weasyprint >=56.1
Requires-Dist: jsonschema >=4.16.0
